CHANGES
LICENSE
MANIFEST.in
README.md
setup.py
vpndnshelper.py
vpndnshelper.egg-info/PKG-INFO
vpndnshelper.egg-info/SOURCES.txt
vpndnshelper.egg-info/dependency_links.txt
vpndnshelper.egg-info/entry_points.txt
vpndnshelper.egg-info/top_level.txt