Metadata-Version: 2.1
Name: vpndnshelper
Version: 0.0.2
Summary: VPN DNS Helper
Home-page: https://github.com/frispete/vpndnshelper
Author: Hans-Peter Jansen
Author-email: hans-peter.jansen@suse.com
License: GNU GPL v2 - see http://www.gnu.org/licenses/gpl2.txt for details
Platform: UNKNOWN
Classifier: Development Status :: 4 - Beta
Classifier: Intended Audience :: System Administrators
Classifier: License :: OSI Approved :: GNU General Public License v2 (GPLv2)
Classifier: Operating System :: POSIX
Classifier: Operating System :: POSIX :: Linux
Classifier: Programming Language :: Python :: 3.3
Classifier: Programming Language :: Python :: 3.4
Classifier: Programming Language :: Python :: 3.5
Classifier: Programming Language :: Python :: 3.6
Classifier: Programming Language :: Python :: 3.7
Classifier: Programming Language :: Python :: 3.8
Requires-Python: >=3
